demo/basic/__main__.py
demo/dw/__main__.py
lilvali/__init__.py
lilvali/__main__.py
lilvali/errors.py
lilvali/binding/__init__.py
lilvali/binding/checker.py
lilvali/binding/config.py
lilvali/binding/struct.py
lilvali/validate/__init__.py
lilvali/validate/checker.py
lilvali/validate/decorators.py
lilvali/validate/validator.py
tests/profiling.py
tests/test_cases.py
tests/test_classes.py
tests/test_lilvali.py
tests/test_newtypes.py
tests/test_validation.py
lilvali-0.1.6.dist-info/METADATA
lilvali-0.1.6.dist-info/WHEEL
lilvali-0.1.6.dist-info/entry_points.txt
lilvali-0.1.6.dist-info/top_level.txt
lilvali-0.1.6.dist-info/RECORD
