Metadata-Version: 2.1
Name: lilvali
Version: 0.1.6
Summary: Tiny validation library for Python
Author-email: Grayson Miller <grayson.miller124@gmail.com>
License: MIT
Project-URL: homepage, https://github.com/GRAYgoose124/lilvali
Classifier: Intended Audience :: Developers
Classifier: Topic :: Utilities
Requires-Python: >=3.12
Provides-Extra: dev
Requires-Dist: black ; extra == 'dev'
Requires-Dist: isort ; extra == 'dev'
Requires-Dist: flake8 ; extra == 'dev'
Requires-Dist: mypy ; extra == 'dev'
Requires-Dist: coverage ; extra == 'dev'
Provides-Extra: dw
Requires-Dist: dataclass-wizard ; extra == 'dw'
